odoo/addons/sale_product_set_variant/README.rst
odoo/addons/sale_product_set_variant/__init__.py
odoo/addons/sale_product_set_variant/__manifest__.py
odoo/addons/sale_product_set_variant/demo/product_product_demo.xml
odoo/addons/sale_product_set_variant/demo/product_set.xml
odoo/addons/sale_product_set_variant/i18n/am.po
odoo/addons/sale_product_set_variant/i18n/ar.po
odoo/addons/sale_product_set_variant/i18n/bg.po
odoo/addons/sale_product_set_variant/i18n/bs.po
odoo/addons/sale_product_set_variant/i18n/ca.po
odoo/addons/sale_product_set_variant/i18n/cs.po
odoo/addons/sale_product_set_variant/i18n/da.po
odoo/addons/sale_product_set_variant/i18n/de.po
odoo/addons/sale_product_set_variant/i18n/el_GR.po
odoo/addons/sale_product_set_variant/i18n/en_GB.po
odoo/addons/sale_product_set_variant/i18n/es.po
odoo/addons/sale_product_set_variant/i18n/es_AR.po
odoo/addons/sale_product_set_variant/i18n/es_CL.po
odoo/addons/sale_product_set_variant/i18n/es_CO.po
odoo/addons/sale_product_set_variant/i18n/es_CR.po
odoo/addons/sale_product_set_variant/i18n/es_DO.po
odoo/addons/sale_product_set_variant/i18n/es_EC.po
odoo/addons/sale_product_set_variant/i18n/es_ES.po
odoo/addons/sale_product_set_variant/i18n/es_MX.po
odoo/addons/sale_product_set_variant/i18n/es_PE.po
odoo/addons/sale_product_set_variant/i18n/es_PY.po
odoo/addons/sale_product_set_variant/i18n/es_VE.po
odoo/addons/sale_product_set_variant/i18n/et.po
odoo/addons/sale_product_set_variant/i18n/eu.po
odoo/addons/sale_product_set_variant/i18n/fa.po
odoo/addons/sale_product_set_variant/i18n/fi.po
odoo/addons/sale_product_set_variant/i18n/fr.po
odoo/addons/sale_product_set_variant/i18n/fr_CA.po
odoo/addons/sale_product_set_variant/i18n/fr_CH.po
odoo/addons/sale_product_set_variant/i18n/gl.po
odoo/addons/sale_product_set_variant/i18n/gl_ES.po
odoo/addons/sale_product_set_variant/i18n/he.po
odoo/addons/sale_product_set_variant/i18n/hr.po
odoo/addons/sale_product_set_variant/i18n/hr_HR.po
odoo12_addon_sale_product_set_variant-12.0.1.1.0.99.dev6.dist-info/METADATA
odoo12_addon_sale_product_set_variant-12.0.1.1.0.99.dev6.dist-info/WHEEL
odoo12_addon_sale_product_set_variant-12.0.1.1.0.99.dev6.dist-info/top_level.txt
odoo12_addon_sale_product_set_variant-12.0.1.1.0.99.dev6.dist-info/RECORD
