Metadata-Version: 2.1
Name: odoo12-addon-sale-product-set-variant
Version: 12.0.1.1.0.99.dev6
Summary: Add variant management to sale product set.
Home-page: https://github.com/OCA/sale-workflow
Author: Camptocamp, Odoo Community Association (OCA)
Author-email: support@odoo-community.org
License: AGPL-3
Platform: UNKNOWN
Classifier: Programming Language :: Python
Classifier: Framework :: Odoo
Classifier: Framework :: Odoo :: 12.0
Classifier: License :: OSI Approved :: GNU Affero General Public License v3
Requires-Python: >=3.5
Requires-Dist: odoo12-addon-sale-product-set
Requires-Dist: odoo <12.1dev,>=12.0a
